nomenklatura/__init__.py
nomenklatura/cache.py
nomenklatura/cli.py
nomenklatura/conflicting_match.py
nomenklatura/db.py
nomenklatura/delta.py
nomenklatura/exceptions.py
nomenklatura/judgement.py
nomenklatura/kv.py
nomenklatura/py.typed
nomenklatura/settings.py
nomenklatura/util.py
nomenklatura/versions.py
nomenklatura/xref.py
nomenklatura/blocker/__init__.py
nomenklatura/blocker/index.py
nomenklatura/blocker/tokenizer.py
nomenklatura/data/er-unstable.pkl
nomenklatura/data/regression-v1.pkl
nomenklatura/enrich/README.md
nomenklatura/enrich/__init__.py
nomenklatura/enrich/aleph.py
nomenklatura/enrich/brightquery.py
nomenklatura/enrich/common.py
nomenklatura/enrich/nominatim.py
nomenklatura/enrich/opencorporates.py
nomenklatura/enrich/openfigi.py
nomenklatura/enrich/permid.py
nomenklatura/enrich/wikidata.py
nomenklatura/enrich/yente.py
nomenklatura/matching/__init__.py
nomenklatura/matching/bench.py
nomenklatura/matching/compat.py
nomenklatura/matching/pairs.py
nomenklatura/matching/types.py
nomenklatura/matching/util.py
nomenklatura/matching/compare/__init__.py
nomenklatura/matching/compare/addresses.py
nomenklatura/matching/compare/countries.py
nomenklatura/matching/compare/dates.py
nomenklatura/matching/compare/gender.py
nomenklatura/matching/compare/identifiers.py
nomenklatura/matching/compare/names.py
nomenklatura/matching/compare/util.py
nomenklatura/matching/erun/__init__.py
nomenklatura/matching/erun/countries.py
nomenklatura/matching/erun/dob.py
nomenklatura/matching/erun/identifiers.py
nomenklatura/matching/erun/misc.py
nomenklatura/matching/erun/model.py
nomenklatura/matching/erun/names.py
nomenklatura/matching/erun/train.py
nomenklatura/matching/erun/util.py
nomenklatura/matching/logic_v1/__init__.py
nomenklatura/matching/logic_v1/identifiers.py
nomenklatura/matching/logic_v1/model.py
nomenklatura/matching/logic_v1/multi.py
nomenklatura/matching/logic_v1/phonetic.py
nomenklatura/matching/logic_v2/__init__.py
nomenklatura/matching/logic_v2/identifiers.py
nomenklatura-4.5.3.dist-info/METADATA
nomenklatura-4.5.3.dist-info/WHEEL
nomenklatura-4.5.3.dist-info/entry_points.txt
nomenklatura-4.5.3.dist-info/licenses/LICENSE
nomenklatura-4.5.3.dist-info/RECORD
