Metadata-Version: 2.4
Name: nomenklatura
Version: 4.5.3
Summary: Make record linkages in followthemoney data.
Project-URL: Documentation, https://github.com/opensanctions/nomenklatura/
Project-URL: Repository, https://github.com/opensanctions/nomenklatura.git
Project-URL: Issues, https://github.com/opensanctions/nomenklatura/issues
Author-email: OpenSanctions <info@opensanctions.org>
License: Copyright (c) 2013-2022, Friedrich Lindenberg
License-File: LICENSE
Classifier: Intended Audience :: Developers
Classifier: License :: OSI Approved :: MIT License
Classifier: Operating System :: OS Independent
Classifier: Programming Language :: Python :: 3.11
Classifier: Programming Language :: Python :: 3.12
Requires-Python: >=3.11
Requires-Dist: click<9.0.0
Requires-Dist: duckdb<2.0.0,>=1.2.0
Requires-Dist: fingerprints<2.0.0,>=1.3.1
Requires-Dist: followthemoney<5.0.0,>=4.5.0
Requires-Dist: lxml<7.0.0,>4.0.0
Requires-Dist: pydantic<3.0.0,>2.0.0
Requires-Dist: rich<15.0.0,>=13.0.0
Requires-Dist: rigour<2.0.0,>=1.6.0
Requires-Dist: scikit-learn==1.7.2
Requires-Dist: shortuuid<2.0.0,>=1.0.11
Requires-Dist: sqlalchemy>=2.0.0
Requires-Dist: textual<5.0.0,>=3.0.0
Provides-Extra: dev
Requires-Dist: build; extra == 'dev'
Requires-Dist: bump2version; extra == 'dev'
Requires-Dist: coverage>=4.1; extra == 'dev'
Requires-Dist: fakeredis; extra == 'dev'
Requires-Dist: flake8>=2.6.0; extra == 'dev'
Requires-Dist: lxml-stubs; extra == 'dev'
Requires-Dist: mypy; extra == 'dev'
Requires-Dist: plyvel<2.0.0; extra == 'dev'
Requires-Dist: psycopg2-binary; extra == 'dev'
Requires-Dist: pytest; extra == 'dev'
Requires-Dist: pytest-cov; extra == 'dev'
Requires-Dist: redis<8.0.0,>5.0.0; extra == 'dev'
Requires-Dist: requests-mock; extra == 'dev'
Requires-Dist: twine; extra == 'dev'
Requires-Dist: types-pyyaml; extra == 'dev'
Requires-Dist: types-redis; extra == 'dev'
Requires-Dist: types-requests; extra == 'dev'
Requires-Dist: types-setuptools; extra == 'dev'
Requires-Dist: wheel>=0.29.0; extra == 'dev'
Provides-Extra: leveldb
Requires-Dist: plyvel<2.0.0; extra == 'leveldb'
Provides-Extra: redis
Requires-Dist: redis<8.0.0,>5.0.0; extra == 'redis'
